chai_lab/__init__.py
chai_lab/chai1.py
chai_lab/main.py
chai_lab/py.typed
chai_lab/data/__init__.py
chai_lab/data/residue_constants.py
chai_lab/data/collate/__init__.py
chai_lab/data/collate/collate.py
chai_lab/data/collate/utils.py
chai_lab/data/dataset/__init__.py
chai_lab/data/dataset/all_atom_feature_context.py
chai_lab/data/dataset/inference_dataset.py
chai_lab/data/dataset/constraints/__init__.py
chai_lab/data/dataset/constraints/restraint_context.py
chai_lab/data/dataset/embeddings/__init__.py
chai_lab/data/dataset/embeddings/embedding_context.py
chai_lab/data/dataset/embeddings/esm.py
chai_lab/data/dataset/msas/__init__.py
chai_lab/data/dataset/msas/colabfold.py
chai_lab/data/dataset/msas/load.py
chai_lab/data/dataset/msas/msa_context.py
chai_lab/data/dataset/msas/preprocess.py
chai_lab/data/dataset/msas/utils.py
chai_lab/data/dataset/structure/all_atom_residue_tokenizer.py
chai_lab/data/dataset/structure/all_atom_structure_context.py
chai_lab/data/dataset/structure/bond_utils.py
chai_lab/data/dataset/structure/chain.py
chai_lab/data/dataset/structure/utils.py
chai_lab/data/dataset/templates/align.py
chai_lab/data/dataset/templates/context.py
chai_lab/data/dataset/templates/load.py
chai_lab/data/features/__init__.py
chai_lab/data/features/feature_factory.py
chai_lab/data/features/feature_type.py
chai_lab/data/features/feature_utils.py
chai_lab/data/features/token_utils.py
chai_lab/data/features/generators/__init__.py
chai_lab/data/features/generators/atom_element.py
chai_lab/data/features/generators/atom_name.py
chai_lab/data/features/generators/base.py
chai_lab/data/features/generators/blocked_atom_pair_distances.py
chai_lab/data/features/generators/docking.py
chai_lab/data/features/generators/esm_generator.py
chai_lab/data/features/generators/identity.py
chai_lab/data/features/generators/is_cropped_chain.py
chai_lab/data/features/generators/missing_chain_contact.py
chai_lab/data/features/generators/msa.py
chai_lab/data/features/generators/ref_pos.py
chai_lab-0.6.1.dist-info/METADATA
chai_lab-0.6.1.dist-info/WHEEL
chai_lab-0.6.1.dist-info/entry_points.txt
chai_lab-0.6.1.dist-info/licenses/LICENSE
chai_lab-0.6.1.dist-info/RECORD
